bin_packing_problem-1.0.0.dist-info/DESCRIPTION.rst
bin_packing_problem-1.0.0.dist-info/METADATA
bin_packing_problem-1.0.0.dist-info/RECORD
bin_packing_problem-1.0.0.dist-info/WHEEL
bin_packing_problem-1.0.0.dist-info/metadata.json
bin_packing_problem-1.0.0.dist-info/top_level.txt
binpackp/__init__.py
binpackp/bins.py
binpackp/fit.py
