Metadata-Version: 2.0
Name: bin-packing-problem
Version: 1.0.0
Summary: Provides 1D bin packing logic.
Home-page: https://github.com/ibigpapa/bin_packing_problem
Author: ibigpapa
Author-email: issues@github.url
License: MIT
Keywords: 1D Bin Packing FirstFit NextFit BestFit FFD
Platform: UNKNOWN
Classifier: Development Status :: 5 - Production/Stable
Classifier: Intended Audience :: Developers
Classifier: License :: OSI Approved :: MIT License
Classifier: Natural Language :: English
Classifier: Programming Language :: Python :: 3.5
Classifier: Topic :: Software Development :: Libraries
